oauthadmin/__init__.py
oauthadmin/adminsite.py
oauthadmin/middleware.py
oauthadmin/settings.py
oauthadmin/urls.py
oauthadmin/utils.py
oauthadmin/views.py
django_admin_oauth2-1.3.1.dist-info/METADATA
django_admin_oauth2-1.3.1.dist-info/WHEEL
django_admin_oauth2-1.3.1.dist-info/top_level.txt
django_admin_oauth2-1.3.1.dist-info/RECORD
