Metadata-Version: 2.1
Name: django-admin-oauth2
Version: 1.3.1
Summary: A django app that replaces the django admin authentication mechanism by deferring to an oauth2 provider
Home-page: https://github.com/RealGeeks/django-admin-oauth2
Author: Real Geeks LLC
Author-email: andrew@realgeeks.com
License: MIT
Classifier: Environment :: Web Environment
Classifier: Framework :: Django
Classifier: Intended Audience :: Developers
Classifier: License :: OSI Approved :: MIT License
Classifier: Operating System :: OS Independent
Classifier: Programming Language :: Python
Requires-Dist: oauthlib
Requires-Dist: requests-oauthlib
